ganymed/__init__.py
ganymed/bootloader/__init__.py
ganymed/bootloader/bootloader.py
ganymed/bootloader/generate_ganymed_image.py
ganymed/bootloader/logging_module.py
ganymed/bootloader/sy1xx_bootloader.py
ganymed/bootloader/threaded_serial_port_handler.py
ganymed/bootloader/firmware/coreguard-debug.bin
ganymed/bootloader/firmware/coreguard-flash.bin
ganymed-0.1.18.dist-info/LICENSE
ganymed-0.1.18.dist-info/METADATA
ganymed-0.1.18.dist-info/WHEEL
ganymed-0.1.18.dist-info/top_level.txt
ganymed-0.1.18.dist-info/RECORD
