Metadata-Version: 2.2
Name: ganymed
Version: 0.1.18
Summary: Sensry Ganymed Sy1xx Package
Author-email: Sven Ginka <s.ginka@sensry.de>
License: Apache License
Project-URL: Homepage, https://github.com/sensry-de/ganymed-pypi
License-File: LICENSE
Requires-Dist: pyserial
